Workbook

Sheet Backlog Backend
A1: ID | B1: Épica | C1: HU | D1: Tarea Backend | E1: Prioridad | F1: Módulo | G1: Responsable | H1: Estado | I1: Notas
A2: T-B00-1 | B2: Entorno y Documentación | C2: — | D2: Inicializar proyecto NestJS con estructura por módulos | E2: Alta | F2: Infraestructura | H2: Done | I2: Base del Hito 1
A3: T-B00-2 | B3: Entorno y Documentación | C3: — | D3: Configurar ValidationPipe global y CORS | E3: Alta | F3: Infraestructura | H3: Done
A4: T-B00-3 | B4: Entorno y Documentación | C4: — | D4: Habilitar documentación OpenAPI/Swagger | E4: Alta | F4: Infraestructura | H4: Done | I4: Disponible en /docs
A5: T-B00-4 | B5: Entorno y Documentación | C5: — | D5: Definir estrategia de ramas (CONTRIBUTING.md) | E5: Media | F5: Infraestructura | H5: Done
A6: T-B00-5 | B6: Entorno y Documentación | C6: — | D6: Escribir README con instrucciones de instalación | E6: Media | F6: Infraestructura | H6: Done
A7: T-B00-6 | B7: Entorno y Documentación | C7: — | D7: Publicar repositorio y crear tag hito-1 | E7: Alta | F7: Infraestructura | H7: Backlog | I7: Requiere acción manual en GitHub
A8: T-B01-1 | B8: Catálogo de Libros | C8: HU-001 | D8: Modelar entidad Libro y DTOs de entrada/salida | E8: Alta | F8: libros | H8: Done
A9: T-B01-2 | B9: Catálogo de Libros | C9: HU-001 | D9: Endpoint POST /libros | E9: Alta | F9: libros | H9: Done
A10: T-B01-3 | B10: Catálogo de Libros | C10: HU-001 | D10: Endpoints GET /libros y GET /libros/:id | E10: Alta | F10: libros | H10: Done
A11: T-B01-4 | B11: Catálogo de Libros | C11: HU-001 | D11: Endpoints PATCH y DELETE /libros/:id | E11: Media | F11: libros | H11: Done
A12: T-B01-5 | B12: Catálogo de Libros | C12: HU-001 | D12: Integrar Open Library para importar por ISBN | E12: Alta | F12: libros | H12: Done | I12: Desafío específico del proyecto
A13: T-B01-6 | B13: Catálogo de Libros | C13: HU-001 | D13: Modelar campo estado (disponible / preventa) | E13: Media | F13: libros | H13: Done | I13: Origen: Site Map
A14: T-B02-1 | B14: Catálogo de Libros | C14: HU-002 | D14: Endpoint de filtro por género y autor | E14: Alta | F14: libros | H14: Done
A15: T-B02-2 | B15: Catálogo de Libros | C15: HU-002 | D15: DTO de parámetros de búsqueda | E15: Media | F15: libros | H15: Done
A16: T-B02-3 | B16: Catálogo de Libros | C16: HU-002 | D16: Definir paginación y orden con UX/UI | E16: Media | F16: libros | H16: In review | I16: Hito 2: page, limit y orden implementados. Falta validar con UX/UI
A17: T-B03-1 | B17: Catálogo de Libros | C17: HU-003 | D17: Confirmar taxonomía de géneros con UX/UI | E17: Media | F17: libros | H17: Backlog
A18: T-B03-2 | B18: Catálogo de Libros | C18: HU-003 | D18: Endpoint de listado de categorías disponibles | E18: Baja | F18: libros | H18: In review | I18: Hito 2: GET /libros/generos
A19: T-B04-1 | B19: Catálogo de Libros | C19: HU-004 | D19: Extender filtros (precio, formato, disponibilidad) | E19: Media | F19: libros | H19: In review | I19: Hito 2: precioMin, precioMax, formato, estado, enStock
A20: T-B05-1 | B20: Motor de Recomendaciones ★ | C20: HU-005 | D20: Diseñar lógica de scoring (género + historial) | E20: Alta | F20: recomendaciones | H20: Done | I20: Esfuerzo diferencial
A21: T-B05-2 | B21: Motor de Recomendaciones ★ | C21: HU-005 | D21: Endpoint GET /recomendaciones/usuario/:id | E21: Alta | F21: recomendaciones | H21: Done | I21: Esfuerzo diferencial
A22: T-B05-3 | B22: Motor de Recomendaciones ★ | C22: HU-005 | D22: Endpoint simulado de registro de compras | E22: Media | F22: recomendaciones | H22: Done
A23: T-B05-4 | B23: Motor de Recomendaciones ★ | C23: HU-005 | D23: Conectar motor al sistema real de Pedidos | E23: Alta | F23: recomendaciones | H23: In review | I23: Hito 2: usa pedidos PAGADOS. Se elimina el endpoint de compras simuladas
A24: T-B06-1 | B24: Perfiles de Librero | C24: HU-006 | D24: Modelar PerfilLibrero y SeccionCurada | E24: Alta | F24: libreros | H24: Done
A25: T-B06-2 | B25: Perfiles de Librero | C25: HU-006 | D25: CRUD de perfil editorial del librero | E25: Alta | F25: libreros | H25: Done
A26: T-B06-3 | B26: Perfiles de Librero | C26: HU-006 | D26: Endpoint de sección curada (agregar/listar) | E26: Alta | F26: libreros | H26: Done
A27: T-B06-4 | B27: Perfiles de Librero | C27: HU-006 | D27: Endpoint "seguir librero" | E27: Media | F27: libreros | H27: Done
A28: T-B07-1 | B28: Gestión de Usuarios | C28: HU-007 | D28: Modelar entidad Usuario y roles | E28: Alta | F28: usuarios | H28: Done
A29: T-B07-2 | B29: Gestión de Usuarios | C29: HU-007 | D29: Endpoint de registro (POST /usuarios) | E29: Alta | F29: usuarios | H29: Done
A30: T-B07-3 | B30: Gestión de Usuarios | C30: HU-007 | D30: Endpoint de login (token simulado) | E30: Alta | F30: usuarios | H30: Done | I30: JWT real pendiente
A31: T-B07-4 | B31: Gestión de Usuarios | C31: HU-007 | D31: Implementar JWT real y guards por rol | E31: Alta | F31: usuarios | H31: In review | I31: Hito 2: JWT real, guard global, @Public y @Roles
A32: T-B07-5 | B32: Gestión de Usuarios | C32: HU-007 | D32: Campo avatarUrl y selección de intereses | E32: Media | F32: usuarios | H32: Done | I32: Origen: Site Map
A33: T-B08-1 | B33: Club de Lectura ★ | C33: HU-008 | D33: Modelar Club, Hilo, Comentario y Progreso | E33: Alta | F33: club-lectura | H33: Done | I33: Esfuerzo diferencial
A34: T-B08-2 | B34: Club de Lectura ★ | C34: HU-008 | D34: CRUD de clubes de lectura | E34: Alta | F34: club-lectura | H34: Done | I34: Esfuerzo diferencial
A35: T-B08-3 | B35: Club de Lectura ★ | C35: HU-008 | D35: Endpoints de hilos de discusión y comentarios | E35: Alta | F35: club-lectura | H35: Done | I35: Esfuerzo diferencial
A36: T-B08-4 | B36: Club de Lectura ★ | C36: HU-008 | D36: Endpoint de progreso de lectura compartido | E36: Media | F36: club-lectura | H36: Done | I36: Esfuerzo diferencial
A37: T-B09-1 | B37: Reseñas | C37: HU-009 | D37: Modelar entidad Reseña | E37: Alta | F37: resenas | H37: Done
A38: T-B09-2 | B38: Reseñas | C38: HU-009 | D38: CRUD de reseñas por libro | E38: Alta | F38: resenas | H38: Done
A39: T-B09-3 | B39: Reseñas | C39: HU-009 | D39: Endpoint "mis reseñas" por usuario | E39: Media | F39: resenas | H39: Done | I39: Origen: Site Map
A40: T-B09-4 | B40: Reseñas | C40: HU-009 | D40: Validar reseña contra historial de compras real | E40: Media | F40: resenas | H40: Backlog | I40: Depende de HU-011
A41: T-B10-1 | B41: Listas de Deseos | C41: HU-010 | D41: Modelar entidad ListaDeseos | E41: Alta | F41: listas-deseos | H41: Done
A42: T-B10-2 | B42: Listas de Deseos | C42: HU-010 | D42: CRUD de listas de deseos | E42: Alta | F42: listas-deseos | H42: Done
A43: T-B10-3 | B43: Listas de Deseos | C43: HU-010 | D43: Endpoint agregar/quitar libro de la lista | E43: Alta | F43: listas-deseos | H43: Done
A44: T-B10-4 | B44: Listas de Deseos | C44: HU-010 | D44: Flag "para regalo" | E44: Media | F44: listas-deseos | H44: Done
A45: T-B11-1 | B45: Pedidos y Compras | C45: HU-011 | D45: Modelar entidad Pedido y sus estados | E45: Alta | F45: pedidos | H45: In review | I45: Hito 2: PENDIENTE_PAGO, PAGADO, CANCELADO
A46: T-B11-2 | B46: Pedidos y Compras | C46: HU-011 | D46: Endpoint de creación de pedido / carrito | E46: Alta | F46: pedidos | H46: In review | I46: Hito 2: POST /pedidos (checkout desde el carrito)
A47: T-B11-3 | B47: Pedidos y Compras | C47: HU-011 | D47: Conectar historial real con Recomendaciones | E47: Alta | F47: pedidos | H47: In review | I47: Hito 2: recomendaciones lee el historial real
A48: T-B12-1 | B48: Pagos | C48: HU-012 | D48: Evaluar pasarela de pago a integrar | E48: Media | F48: pagos | H48: Backlog
A49: T-B12-2 | B49: Pagos | C49: HU-012 | D49: Endpoint de confirmación de pago | E49: Media | F49: pagos | H49: In review | I49: Hito 2: POST /pagos con pasarela dummy
A50: T-B13-1 | B50: Ofertas y Precios | C50: HU-013 | D50: Modelar descuentos y vigencia en Libro | E50: Baja | F50: libros | H50: Backlog | I50: Origen: Site Map
A51: T-B13-2 | B51: Ofertas y Precios | C51: HU-013 | D51: Endpoint de libros en oferta | E51: Baja | F51: libros | H51: Backlog
A52: T-B14-1 | B52: Newsletter | C52: HU-014 | D52: Modelar suscripción de usuario | E52: Baja | F52: usuarios | H52: Backlog | I52: Origen: Site Map
A53: T-B14-2 | B53: Newsletter | C53: HU-014 | D53: Endpoint de suscripción / desuscripción | E53: Baja | F53: usuarios | H53: Backlog
A54: T-B15-1 | B54: Descubrimiento (Novedades/Ranking) | C54: HU-015 | D54: Campo fechaIngresoCatalogo en Libro | E54: Media | F54: libros | H54: In review | I54: Hito 2: columna fecha_ingreso
A55: T-B15-2 | B55: Descubrimiento (Novedades/Ranking) | C55: HU-015 | D55: Endpoint de novedades ordenadas por fecha | E55: Media | F55: libros | H55: In review | I55: Hito 2: GET /libros?orden=novedades
A56: T-B15-3 | B56: Descubrimiento (Novedades/Ranking) | C56: HU-015 | D56: Endpoint de ranking / top ventas | E56: Baja | F56: pedidos | H56: Backlog | I56: Depende de HU-011
A57: T-B16-1 | B57: Comunidad (Discusiones/Podcast) | C57: HU-016 | D57: Modelar foro general de discusiones | E57: Baja | F57: comunidad | H57: Backlog | I57: Origen: Site Map
A58: T-B16-2 | B58: Comunidad (Discusiones/Podcast) | C58: HU-016 | D58: Modelar contenido de podcast | E58: Baja | F58: comunidad | H58: Backlog | I58: Origen: Site Map
A59: T-B17-1 | B59: Mi Biblioteca (Favoritos/Leídos) | C59: HU-017 | D59: Modelar entidad Favorito | E59: Media | F59: usuarios | H59: Backlog | I59: Distinto de Lista de Deseos
A60: T-B17-2 | B60: Mi Biblioteca (Favoritos/Leídos) | C60: HU-017 | D60: Modelar registro general de lectura | E60: Media | F60: usuarios | H60: Backlog | I60: Origen: Card Sorting
A61: T-B07-6 | B61: Gestión de Usuarios | C61: HU-007 | D61: Contraseñas con bcrypt y rutas /auth/registro, /auth/login, /auth/me | E61: Alta | F61: auth | H61: In review | I61: Hito 2
A62: T-B07-7 | B62: Gestión de Usuarios | C62: HU-007 | D62: Restringir /usuarios al dueño de la cuenta o ADMIN | E62: Alta | F62: usuarios | H62: In review | I62: Hito 2
A63: T-B11-4 | B63: Pedidos y Compras | C63: HU-011 | D63: Checkout transaccional: reserva de stock y copia de precios | E63: Alta | F63: pedidos | H63: In review | I63: Hito 2
A64: T-B11-5 | B64: Pedidos y Compras | C64: HU-011 | D64: Historial, detalle y cancelación con devolución de stock | E64: Alta | F64: pedidos | H64: In review | I64: Hito 2
A65: T-B12-3 | B65: Pagos | C65: HU-012 | D65: Reglas dummy de aprobación/rechazo y registro de intentos | E65: Alta | F65: pagos | H65: In review | I65: Hito 2: ver docs/servicios.md
... A89: T-B23-2 | B89: Integración Web y Mobile | C89: — | D89: Entregar URL base, Swagger y cuentas de prueba | E89: Alta | F89: Infraestructura | H89: Backlog | I89: Depende de T-B22-3

Sheet Resumen
B2: Resumen del Backlog — Backend LeeConNos
B4: Distribución por Estado
B5: Estado | C5: Cantidad de tareas
B6: No Status | C6: =COUNTIF('Backlog Backend'!H:H,B6)
B7: Backlog | C7: =COUNTIF('Backlog Backend'!H:H,B7)
B8: Ready | C8: =COUNTIF('Backlog Backend'!H:H,B8)
B9: In progress | C9: =COUNTIF('Backlog Backend'!H:H,B9)
B10: In review | C10: =COUNTIF('Backlog Backend'!H:H,B10)
B11: Done | C11: =COUNTIF('Backlog Backend'!H:H,B11)
B12: Total | C12: =SUM(C6:C11)
B15: Distribución por Épica
B16: Épica | C16: Cantidad de tareas
B17: Entorno y Documentación | C17: =COUNTIF('Backlog Backend'!B:B,B17)
B18: Catálogo de Libros | C18: =COUNTIF('Backlog Backend'!B:B,B18)
B19: Motor de Recomendaciones ★ | C19: =COUNTIF('Backlog Backend'!B:B,B19)
B20: Perfiles de Librero | C20: =COUNTIF('Backlog Backend'!B:B,B20)
B21: Gestión de Usuarios | C21: =COUNTIF('Backlog Backend'!B:B,B21)
B22: Club de Lectura ★ | C22: =COUNTIF('Backlog Backend'!B:B,B22)
B23: Reseñas | C23: =COUNTIF('Backlog Backend'!B:B,B23)
B24: Listas de Deseos | C24: =COUNTIF('Backlog Backend'!B:B,B24)
B25: Pedidos y Compras | C25: =COUNTIF('Backlog Backend'!B:B,B25)
B26: Pagos | C26: =COUNTIF('Backlog Backend'!B:B,B26)
B27: Ofertas y Precios | C27: =COUNTIF('Backlog Backend'!B:B,B27)
B28: Newsletter | C28: =COUNTIF('Backlog Backend'!B:B,B28)
... B37: Integración Web y Mobile | C37: =COUNTIF('Backlog Backend'!B:B,B37)

Sheet Leyenda
B2: Cómo usar este backlog
B4: • | C4: Esta planilla lista las tareas Backend identificadas en los Hitos 1 y 2 de LeeConNos.
B6: • | C6: Completa la columna "Responsable" (resaltada en amarillo) con el nombre de quien ejecuta cada tarea.
B8: • | C8: Actualiza "Estado" a medida que el trabajo avance, usando los mismos valores del tablero Kanban del equipo.
B10: • | C10: Las filas en "Done" corresponden a servicios ya construidos y probados en el proyecto backend.
B12: • | C12: Las filas en "Backlog" son sistemas identificados pero no implementados aún, o planificados para el siguiente hito.
B15: Prioridad
B16: Alta | C16: Bloquea otras tareas o es parte del esfuerzo diferencial del proyecto
B17: Media | C17: Necesaria para completar la funcionalidad, no bloqueante
B18: Baja | C18: Mejora o extensión, puede esperar a hitos posteriores
B20: Estado
B21: No Status | C21: Sin triage todavía
B22: Backlog | C22: Identificada, trabajo aún no iniciado
B23: Ready | C23: Lista para comenzar
B24: In progress | C24: Trabajo en curso
B25: In review | C25: En revisión (Pull Request abierto)
B26: Done | C26: Construida, probada y documentada
